{
    "meta": {
        "id": "blogg/blog-post-2008.06.01-00.00.00-001",
        "path": "/blogg/blog-post-2008.06.01-00.00.00-001",
        "title": "Marthe er snart klar for…",
        "classification": "content",
        "type": "blog-post",
        "default-template": "blog-post"
    },
    "content": {
        "blog-post": {
            "meta": {
                "blog-format-version": "1.0",
                "time-format-pattern": "dd.MM.yyyy",
                "source": {
                    "type": "vg-blogg",
                    "values": {
                        "vg-blogg-id": "30887", 
                        "vg-blogg-url": "http://30887.vgb.no"
                    }
                }
            },
            "heading": "Marthe er snart klar for…",
            "author": {
                "id": "Sveinung",
                "display-name": "Sveinung"
            },
            "timestamp": "01.06.2008",
            "text-blocks": [
                "Marthe er snart klar for rallykjøring! Litt testkjøring i dag før Aurskog- Høland Rally."
            ],
            "images": [
                {
                    "name": "http://bilder.vgb.no/28756/3col/img_4842bb9fc0ae9.jpg"
                }
            ]
        }
    }
}