{
    "meta": {
        "id": "blogg/blog-post-2011.05.13-10.28.53-001",
        "path": "/blogg/blog-post-2011.05.13-10.28.53-001",
        "title": "Gjennomkjørin",
        "classification": "content",
        "type": "blog-post",
        "default-template": "blog-post"
    },
    "content": {
        "blog-post": {
            "meta": {
                "blog-format-version": "1.0",
                "time-format-pattern": "dd.MM.yyyy HH:mm:ss",
                "source": {
                    "type": "email-based-blog",
                    "values": {
                        "email-account": "srblogg@gmail.com", 
                        "from-address": "rogereilert@hotmail.com", 
                        "to-address": "srblogg@gmail.com", 
                        "subject": "Gjennomkjørin", 
                        "sent-timestamp": "13.05.2011 04:28:26", 
                        "received-timestamp": "13.05.2011 04:28:53", 
                        "message-id": "<BLU0-SMTP1930EB3D4A33222A93D07B6A1880@phx.gbl>"
                    }
                }
            },
            "heading": "Gjennomkjørin",
            "author": {
                "id": "Roger",
                "display-name": "Roger"
            },
            "timestamp": "13.05.2011 10:28:53",
            "text-blocks": [
                "Da har vi gjennomkjøring.. Raske løse veier..", 
                ""
            ],
            "images": [
                {
                    "name": "blog-post-2011.05.13-10.28.53-001-image-1.JPG", 
                    "height": "478", 
                    "width": "640", 
                    "orientation": "Landscape", 
                    "original-name": "bilde.JPG"
                }
            ]
        }
    }
}